LICENSE
MANIFEST.in
README.rst
setup.cfg
setup.py
Mopidy_Spotify_Web.egg-info/PKG-INFO
Mopidy_Spotify_Web.egg-info/SOURCES.txt
Mopidy_Spotify_Web.egg-info/dependency_links.txt
Mopidy_Spotify_Web.egg-info/entry_points.txt
Mopidy_Spotify_Web.egg-info/not-zip-safe
Mopidy_Spotify_Web.egg-info/requires.txt
Mopidy_Spotify_Web.egg-info/top_level.txt
mopidy_spotify_web/__init__.py
mopidy_spotify_web/backend.py
mopidy_spotify_web/ext.conf
mopidy_spotify_web/library.py
mopidy_spotify_web/translator.py