Metadata-Version: 1.1
Name: Mopidy-Spotify-Web
Version: 0.3.0
Summary: Mopidy extension for providing the browse feature of Spotify for artists and albums
Home-page: https://github.com/1234556767899/mopidy-spotify-web
Author: Laurence Cabenda
Author-email: lfcabend@gmail.com
License: Apache License, Version 2.0
Platform: UNKNOWN
Classifier: Environment :: No Input/Output (Daemon)
Classifier: Intended Audience :: End Users/Desktop
Classifier: License :: OSI Approved :: Apache Software License
Classifier: Operating System :: OS Independent
Classifier: Programming Language :: Python :: 2
Classifier: Topic :: Multimedia :: Sound/Audio :: Players
